dash_component_template/__init__.py
dash_component_template/idtree.py
dash_component_template/template.py
dash_component_template-0.2.0.dist-info/AUTHORS.rst
dash_component_template-0.2.0.dist-info/LICENSE
dash_component_template-0.2.0.dist-info/METADATA
dash_component_template-0.2.0.dist-info/WHEEL
dash_component_template-0.2.0.dist-info/top_level.txt
dash_component_template-0.2.0.dist-info/RECORD
