Metadata-Version: 2.1
Name: dash-component-template
Version: 0.2.0
Summary: A framework to create reusable Dash layout.
Home-page: https://github.com/toltec-astro/dash_component_template
Author: Zhiyuan Ma
Author-email: zhiyuanma@umass.edu
License: BSD license
Keywords: dash_component_template
Platform: UNKNOWN
Classifier: Development Status :: 2 - Pre-Alpha
Classifier: Intended Audience :: Developers
Classifier: License :: OSI Approved :: BSD License
Classifier: Natural Language :: English
Classifier: Programming Language :: Python :: 3
Classifier: Programming Language :: Python :: 3.8
Requires-Python: >=3.8
Requires-Dist: anytree
Requires-Dist: numpy
Requires-Dist: dash
Requires-Dist: dash-bootstrap-components
